<?xml version="1.0" encoding="UTF-8"?>
<MF0 version="1.1" packageUris="http://schema.mathworks.com/mf0/ci/19700101 http://schema.mathworks.com/mf0/sl_modelref_info/R2024a http://schema.mathworks.com/mf0/slexec_mm_sto/R2024a_202305081229 http://schema.mathworks.com/mf0/sltp_mm/R2023a_202209151115">
  <ModelRefInfoRepo.ModelRefInfoRoot type="ModelRefInfoRepo.ModelRefInfoRoot" uuid="80aa7c8b-5910-4423-9125-477bb14f3f16">
    <JITEngines>s6P2emLMgs4Utq8T86bWwdB</JITEngines>
    <childModelRefInfo type="ModelRefInfoRepo.ChildModelRefInfo" uuid="8f6c78f6-95d1-468a-8cf1-0c3f50185917">
      <modelName>Propulsor</modelName>
      <modelPath>Propulsor</modelPath>
    </childModelRefInfo>
    <compDerivCacheNeedsReset>false</compDerivCacheNeedsReset>
    <compZcCacheNeedsReset>false</compZcCacheNeedsReset>
    <compiledTFinal>68124.0</compiledTFinal>
    <dataSourceInfo type="ModelRefInfoRepo.DataSourceInfo" uuid="b2941875-f612-44bf-903d-de21928aabaa">
      <dataSources type="ModelRefInfoRepo.SourceInfo" uuid="971e168d-c48c-41fa-8422-d11b006b6da7">
        <includeAllSections>true</includeAllSections>
        <sourceName>base workspace</sourceName>
        <type>BaseWorkspace</type>
      </dataSources>
      <modelName>Propulsor</modelName>
    </dataSourceInfo>
    <dataTransferInfos>AAFJTQAAAAAOAAAAOAAAAAYAAAAIAAAAAgAAAAAAAAAFAAAACAAAAAAAAAABAAAAAQAAAAAAAAAFAAQAAQAAAAEAAAAAAAAA</dataTransferInfos>
    <defaultsCMapping>{&quot;Inports&quot;:&quot;{\&quot;Name\&quot;:\&quot;Default\&quot;,\&quot;Checksum\&quot;:\&quot;Default\&quot;,\&quot;PerInstancePropertiesChecksum\&quot;:\&quot;\&quot;,\&quot;MemorySectionName\&quot;:\&quot;None\&quot;,\&quot;MemorySectionChecksum\&quot;:\&quot;None\&quot;}&quot;,&quot;Outports&quot;:&quot;{\&quot;Name\&quot;:\&quot;Default\&quot;,\&quot;Checksum\&quot;:\&quot;Default\&quot;,\&quot;PerInstancePropertiesChecksum\&quot;:\&quot;\&quot;,\&quot;MemorySectionName\&quot;:\&quot;None\&quot;,\&quot;MemorySectionChecksum\&quot;:\&quot;None\&quot;}&quot;,&quot;ParameterArguments&quot;:&quot;{\&quot;Name\&quot;:\&quot;Default\&quot;,\&quot;Checksum\&quot;:\&quot;Default\&quot;,\&quot;PerInstancePropertiesChecksum\&quot;:\&quot;\&quot;,\&quot;MemorySectionName\&quot;:\&quot;None\&quot;,\&quot;MemorySectionChecksum\&quot;:\&quot;None\&quot;}&quot;,&quot;LocalParameters&quot;:&quot;{\&quot;Name\&quot;:\&quot;Default\&quot;,\&quot;Checksum\&quot;:\&quot;Default\&quot;,\&quot;PerInstancePropertiesChecksum\&quot;:\&quot;\&quot;,\&quot;MemorySectionName\&quot;:\&quot;None\&quot;,\&quot;MemorySectionChecksum\&quot;:\&quot;None\&quot;}&quot;,&quot;GlobalParameters&quot;:&quot;{\&quot;Name\&quot;:\&quot;Default\&quot;,\&quot;Checksum\&quot;:\&quot;Default\&quot;,\&quot;PerInstancePropertiesChecksum\&quot;:\&quot;\&quot;,\&quot;MemorySectionName\&quot;:\&quot;None\&quot;,\&quot;MemorySectionChecksum\&quot;:\&quot;None\&quot;}&quot;,&quot;InternalData&quot;:&quot;{\&quot;Name\&quot;:\&quot;Default\&quot;,\&quot;Checksum\&quot;:\&quot;Default\&quot;,\&quot;PerInstancePropertiesChecksum\&quot;:\&quot;\&quot;,\&quot;MemorySectionName\&quot;:\&quot;None\&quot;,\&quot;MemorySectionChecksum\&quot;:\&quot;None\&quot;}&quot;,&quot;SharedLocalDataStores&quot;:&quot;{\&quot;Name\&quot;:\&quot;Default\&quot;,\&quot;Checksum\&quot;:\&quot;Default\&quot;,\&quot;PerInstancePropertiesChecksum\&quot;:\&quot;\&quot;,\&quot;MemorySectionName\&quot;:\&quot;None\&quot;,\&quot;MemorySectionChecksum\&quot;:\&quot;None\&quot;}&quot;,&quot;GlobalDataStores&quot;:&quot;{\&quot;Name\&quot;:\&quot;Default\&quot;,\&quot;Checksum\&quot;:\&quot;Default\&quot;,\&quot;PerInstancePropertiesChecksum\&quot;:\&quot;\&quot;,\&quot;MemorySectionName\&quot;:\&quot;None\&quot;,\&quot;MemorySectionChecksum\&quot;:\&quot;None\&quot;}&quot;,&quot;Constants&quot;:&quot;{\&quot;Name\&quot;:\&quot;Default\&quot;,\&quot;Checksum\&quot;:\&quot;Default\&quot;,\&quot;PerInstancePropertiesChecksum\&quot;:\&quot;\&quot;,\&quot;MemorySectionName\&quot;:\&quot;None\&quot;,\&quot;MemorySectionChecksum\&quot;:\&quot;None\&quot;}&quot;,&quot;DataTransfers&quot;:&quot;{\&quot;Name\&quot;:\&quot;Default\&quot;,\&quot;Checksum\&quot;:\&quot;Default\&quot;,\&quot;PerInstancePropertiesChecksum\&quot;:\&quot;\&quot;,\&quot;MemorySectionName\&quot;:\&quot;None\&quot;,\&quot;MemorySectionChecksum\&quot;:\&quot;None\&quot;}&quot;,&quot;ModelData&quot;:&quot;{\&quot;Name\&quot;:\&quot;Default\&quot;,\&quot;Checksum\&quot;:\&quot;Default\&quot;,\&quot;PerInstancePropertiesChecksum\&quot;:\&quot;\&quot;,\&quot;MemorySectionName\&quot;:\&quot;None\&quot;,\&quot;MemorySectionChecksum\&quot;:\&quot;None\&quot;}&quot;,&quot;InitializeTerminate&quot;:&quot;{\&quot;Name\&quot;:\&quot;Default\&quot;,\&quot;Checksum\&quot;:\&quot;Default\&quot;,\&quot;PerInstancePropertiesChecksum\&quot;:\&quot;\&quot;,\&quot;MemorySectionName\&quot;:\&quot;None\&quot;,\&quot;MemorySectionChecksum\&quot;:\&quot;None\&quot;}&quot;,&quot;Execution&quot;:&quot;{\&quot;Name\&quot;:\&quot;Default\&quot;,\&quot;Checksum\&quot;:\&quot;Default\&quot;,\&quot;PerInstancePropertiesChecksum\&quot;:\&quot;\&quot;,\&quot;MemorySectionName\&quot;:\&quot;None\&quot;,\&quot;MemorySectionChecksum\&quot;:\&quot;None\&quot;}&quot;,&quot;SharedUtility&quot;:&quot;{\&quot;Name\&quot;:\&quot;Default\&quot;,\&quot;Checksum\&quot;:\&quot;Default\&quot;,\&quot;PerInstancePropertiesChecksum\&quot;:\&quot;\&quot;,\&quot;MemorySectionName\&quot;:\&quot;None\&quot;,\&quot;MemorySectionChecksum\&quot;:\&quot;None\&quot;}&quot;}</defaultsCMapping>
    <fastestNoncontSigFeedingDerivPorts>.01</fastestNoncontSigFeedingDerivPorts>
    <globalVariables>Fn</globalVariables>
    <globalVariables>Td</globalVariables>
    <globalVariables>Tpulse</globalVariables>
    <globalVariables>mib</globalVariables>
    <globalVariables>peak_prop</globalVariables>
    <globalVariables>step_modelo</globalVariables>
    <globalVariables>tc</globalVariables>
    <globalVariables>tf</globalVariables>
    <grCompInputPortMaps>0,0,0</grCompInputPortMaps>
    <grCompOutputPortMaps>0,0,0</grCompOutputPortMaps>
    <hasBlockWithPeriodicDiscreteSampleTime>true</hasBlockWithPeriodicDiscreteSampleTime>
    <hasBwsAccessed>true</hasBwsAccessed>
    <hasConstantOutput>false</hasConstantOutput>
    <hasContinuousSampleTime>true</hasContinuousSampleTime>
    <hasModelWideEventTs>false</hasModelWideEventTs>
    <hasNoncontSigFeedingDerivPorts>true</hasNoncontSigFeedingDerivPorts>
    <hasParallelForEachBlocker>true</hasParallelForEachBlocker>
    <inports type="ModelRefInfoRepo.InportInformation" uuid="2fa658f0-4e4a-4a21-9b87-b46fe7e232ea">
      <globalInRTW>false</globalInRTW>
      <isNotDerivPort>true</isNotDerivPort>
      <overWritable>false</overWritable>
      <designMax>inf</designMax>
      <designMin>-inf</designMin>
      <indexType>2</indexType>
      <rateInfos type="ModelRefInfoRepo.RateInfo">
        <compiled>true</compiled>
        <needAbsoluteTime>true</needAbsoluteTime>
        <period>0.0</period>
        <priority>40</priority>
        <rateIdx>0</rateIdx>
      </rateInfos>
      <resolvedSignalObject></resolvedSignalObject>
      <executionInterface type="ModelRefInfoRepo.InputExecutionInterface" uuid="4de3a28f-fd76-4520-a8ae-1a941e9697cb"/>
      <sigNameToEMVCEMap type="ModelRefInfoRepo.SigNameEMVCEInfo" uuid="ccfe6fdb-c70c-435c-a66f-8d6a22369f52"/>
    </inports>
    <isAperiodicRootFcnCallSystem>false</isAperiodicRootFcnCallSystem>
    <isOrigInportVirtualBus>false</isOrigInportVirtualBus>
    <isOrigOutportVirtualBus>false</isOrigOutportVirtualBus>
    <isPreCompSingleRate>false</isPreCompSingleRate>
    <isRefModelConstant>false</isRefModelConstant>
    <isRootFcnCallPortGroupsEmpty>true</isRootFcnCallPortGroupsEmpty>
    <loggingSaveFormat>2</loggingSaveFormat>
    <massMatrixNzMax>1</massMatrixNzMax>
    <maxFreqHz>-1.0</maxFreqHz>
    <needAbsoluteTimeDisallowInitPort>true</needAbsoluteTimeDisallowInitPort>
    <needsAbsoluteTime>true</needsAbsoluteTime>
    <nonTunableVariables>Td</nonTunableVariables>
    <nonTunableVariables>step_modelo</nonTunableVariables>
    <numCStateRecs>1</numCStateRecs>
    <numContinuousStates>1</numContinuousStates>
    <numDStateRecs>3</numDStateRecs>
    <numDataInputPorts>1</numDataInputPorts>
    <numLoggableCStateRecs>1</numLoggableCStateRecs>
    <numLoggableDStateRecs>3</numLoggableDStateRecs>
    <numLoggableJacobianDStates>12</numLoggableJacobianDStates>
    <numModelWideEventTs>0</numModelWideEventTs>
    <numPortlessSimulinkFunctionPortGroups>0</numPortlessSimulinkFunctionPortGroups>
    <numRuntimeExportedRates>2</numRuntimeExportedRates>
    <numTs>2</numTs>
    <origInportBusType></origInportBusType>
    <origOutportBusOutputAsStruct>false</origOutportBusOutputAsStruct>
    <origOutportBusType></origOutportBusType>
    <outports type="ModelRefInfoRepo.OutportInformation" uuid="0cc35b6f-19b8-47dc-a42c-2f77e2138fb8">
      <blkIOUpdatedInAnotherExecContext>true</blkIOUpdatedInAnotherExecContext>
      <hasSystemInitMethod>true</hasSystemInitMethod>
      <isInitializedWithIC>true</isInitializedWithIC>
      <nonContSigSizeInBytes>8</nonContSigSizeInBytes>
      <nonContinuous>true</nonContinuous>
      <numNonContSigs>1</numNonContSigs>
      <okToMerge>1</okToMerge>
      <designMax>inf</designMax>
      <designMin>-inf</designMin>
      <indexType>2</indexType>
      <rateInfos type="ModelRefInfoRepo.RateInfo">
        <compiled>true</compiled>
        <needAbsoluteTime>true</needAbsoluteTime>
        <period>0.0</period>
        <priority>40</priority>
        <rateIdx>0</rateIdx>
      </rateInfos>
      <resolvedSignalObject></resolvedSignalObject>
      <executionInterface type="ModelRefInfoRepo.OutputExecutionInterface" uuid="33b731b5-2ef5-4f1a-8884-d695280c252e"/>
      <sigNameToEMVCEMap type="ModelRefInfoRepo.SigNameEMVCEInfo" uuid="9da0bf54-493d-4eb7-b1d2-e1b00c66ddad"/>
    </outports>
    <preCompAllowConstTsOnPorts>false</preCompAllowConstTsOnPorts>
    <preCompAllowPortBasedInTriggeredSS>false</preCompAllowPortBasedInTriggeredSS>
    <runtimeNonFcnCallRateInfos type="ModelRefInfoRepo.RateInfo">
      <compiled>true</compiled>
      <needAbsoluteTime>true</needAbsoluteTime>
      <period>0.0</period>
      <priority>40</priority>
      <rateIdx>0</rateIdx>
    </runtimeNonFcnCallRateInfos>
    <runtimeNonFcnCallRateInfos type="ModelRefInfoRepo.RateInfo">
      <compiled>true</compiled>
      <nonFcnCallPartitionName>Cont</nonFcnCallPartitionName>
      <period>.01</period>
      <priority>40</priority>
      <rateIdx>1</rateIdx>
    </runtimeNonFcnCallRateInfos>
    <sampleTimeInheritanceRule>2</sampleTimeInheritanceRule>
    <solverStatusFlags>327</solverStatusFlags>
    <timingAndTaskingRegistry>&lt;?xml version=&quot;1.0&quot;?&gt;
&lt;slexec_sto version=&quot;1.1&quot; packageUris=&quot;http://schema.mathworks.com/mf0/slexec_mm_sto/R2024a_202305081229&quot;&gt;
  &lt;sto.Registry type=&quot;sto.Registry&quot; uuid=&quot;d68927af-2ba0-4153-b6d2-dd8da4419038&quot;&gt;
    &lt;executionSpec&gt;Undetermined&lt;/executionSpec&gt;
    &lt;identifier&gt;Propulsor&lt;/identifier&gt;
    &lt;clockRegistry type=&quot;sto.ClockRegistry&quot; uuid=&quot;c229538b-f7c2-43c1-80bd-d85f90eabc97&quot;&gt;
      &lt;clocks type=&quot;sto.Timer&quot; uuid=&quot;76fb724a-8577-4951-a448-9b9202bee9c4&quot;&gt;
        &lt;computedFundamentalDiscretePeriod&gt;.01&lt;/computedFundamentalDiscretePeriod&gt;
        &lt;fastestDiscreteRate type=&quot;sto.ClassicPeriodicDiscreteRate&quot; uuid=&quot;df79e5f3-efed-40d0-9246-c80644ce0dbf&quot;/&gt;
        &lt;isDefaultTimer&gt;true&lt;/isDefaultTimer&gt;
        &lt;resolution&gt;.01&lt;/resolution&gt;
        &lt;timeAdvanceMode&gt;FixedStep&lt;/timeAdvanceMode&gt;
        &lt;identifier&gt;Propulsor::defaultTimer&lt;/identifier&gt;
        &lt;rates type=&quot;sto.ContinuousRate&quot; uuid=&quot;53a39c1e-a6be-4181-af3d-8c5c8475db84&quot;&gt;
          &lt;annotation&gt;Cont&lt;/annotation&gt;
          &lt;clockId&gt;Propulsor::defaultTimer&lt;/clockId&gt;
          &lt;colorIndex&gt;-1&lt;/colorIndex&gt;
          &lt;description&gt;Continuous&lt;/description&gt;
          &lt;taskId&gt;_task0&lt;/taskId&gt;
          &lt;rateSpec type=&quot;sto.RateSpec&quot; uuid=&quot;0011f68c-976e-406b-87ff-9a469214732f&quot;/&gt;
        &lt;/rates&gt;
        &lt;rates type=&quot;sto.ClassicPeriodicDiscreteRate&quot; uuid=&quot;df79e5f3-efed-40d0-9246-c80644ce0dbf&quot;&gt;
          &lt;annotation&gt;D1&lt;/annotation&gt;
          &lt;clockId&gt;Propulsor::defaultTimer&lt;/clockId&gt;
          &lt;description&gt;Discrete 1&lt;/description&gt;
          &lt;rateIdx&gt;1&lt;/rateIdx&gt;
          &lt;taskId&gt;_task0&lt;/taskId&gt;
          &lt;rateSpec type=&quot;sto.RateSpec&quot; uuid=&quot;738dbf1d-57c6-43c3-a7ed-cc31b4aad998&quot;&gt;
            &lt;period&gt;.01&lt;/period&gt;
            &lt;rateType&gt;ClassicPeriodicDiscrete&lt;/rateType&gt;
          &lt;/rateSpec&gt;
        &lt;/rates&gt;
        &lt;baseRate type=&quot;sto.ContinuousRate&quot; uuid=&quot;506739f9-7c1e-48f6-97d1-23b8f5e4a8e5&quot;&gt;
          &lt;annotation&gt;Cont&lt;/annotation&gt;
          &lt;clockId&gt;Propulsor::defaultTimer&lt;/clockId&gt;
          &lt;colorIndex&gt;-1&lt;/colorIndex&gt;
          &lt;description&gt;Continuous&lt;/description&gt;
          &lt;taskId&gt;_task0&lt;/taskId&gt;
          &lt;rateSpec type=&quot;sto.RateSpec&quot; uuid=&quot;e0ebb733-3050-41d5-8600-447842508073&quot;/&gt;
        &lt;/baseRate&gt;
      &lt;/clocks&gt;
      &lt;timeAdvanceMode&gt;FixedStep&lt;/timeAdvanceMode&gt;
    &lt;/clockRegistry&gt;
    &lt;taskRegistry type=&quot;sto.TaskRegistry&quot; uuid=&quot;75dab8a4-16c6-46dd-b5e7-e1ae3c7c681f&quot;&gt;
      &lt;rootTaskHierarchyElements type=&quot;sto.Task&quot; uuid=&quot;8f19c440-2d77-403c-b1a9-a0934e977852&quot;&gt;
        &lt;isExecutable&gt;true&lt;/isExecutable&gt;
        &lt;orderIndex&gt;1&lt;/orderIndex&gt;
        &lt;rates type=&quot;sto.ContinuousRate&quot; uuid=&quot;e46fbbc8-7aaf-4c67-ae9b-05eb736872fc&quot;&gt;
          &lt;annotation&gt;Cont&lt;/annotation&gt;
          &lt;clockId&gt;Propulsor::defaultTimer&lt;/clockId&gt;
          &lt;colorIndex&gt;-1&lt;/colorIndex&gt;
          &lt;description&gt;Continuous&lt;/description&gt;
          &lt;taskId&gt;_task0&lt;/taskId&gt;
          &lt;rateSpec type=&quot;sto.RateSpec&quot; uuid=&quot;c37b9531-5913-4b77-af25-ba3684e7912a&quot;/&gt;
        &lt;/rates&gt;
        &lt;rates type=&quot;sto.ClassicPeriodicDiscreteRate&quot; uuid=&quot;0262314c-9ee5-4b52-93c7-ecbd6fee538e&quot;&gt;
          &lt;annotation&gt;D1&lt;/annotation&gt;
          &lt;clockId&gt;Propulsor::defaultTimer&lt;/clockId&gt;
          &lt;description&gt;Discrete 1&lt;/description&gt;
          &lt;rateIdx&gt;1&lt;/rateIdx&gt;
          &lt;taskId&gt;_task0&lt;/taskId&gt;
          &lt;rateSpec type=&quot;sto.RateSpec&quot; uuid=&quot;f020dd00-a8c4-41a8-8835-006acccab568&quot;&gt;
            &lt;period&gt;.01&lt;/period&gt;
            &lt;rateType&gt;ClassicPeriodicDiscrete&lt;/rateType&gt;
          &lt;/rateSpec&gt;
        &lt;/rates&gt;
        &lt;schedulingClockId&gt;Propulsor::defaultTimer&lt;/schedulingClockId&gt;
        &lt;timeKeeperClockId&gt;Propulsor::defaultTimer&lt;/timeKeeperClockId&gt;
        &lt;elementType&gt;Task&lt;/elementType&gt;
        &lt;identifier&gt;_task0&lt;/identifier&gt;
        &lt;priority&gt;40&lt;/priority&gt;
      &lt;/rootTaskHierarchyElements&gt;
      &lt;taskDependencyGraph type=&quot;sto.SerializedTaskConnectionList&quot; uuid=&quot;216d838b-80fa-4fdb-9cb6-6086c87b8780&quot;&gt;
        &lt;clockIdentifier&gt;Propulsor::defaultTimer&lt;/clockIdentifier&gt;
        &lt;taskIdentifier&gt;_task0&lt;/taskIdentifier&gt;
      &lt;/taskDependencyGraph&gt;
      &lt;taskPriorityDirection&gt;HighNumberLast&lt;/taskPriorityDirection&gt;
    &lt;/taskRegistry&gt;
  &lt;/sto.Registry&gt;
&lt;/slexec_sto&gt;</timingAndTaskingRegistry>
    <usePortBasedSampleTime>false</usePortBasedSampleTime>
    <userSpecifiedFixedStepSize>.01</userSpecifiedFixedStepSize>
    <FMUBlockMap type="ModelRefInfoRepo.FMUBlockInfo" uuid="09a32aa9-9046-4b9a-8799-0e41687c3695"/>
    <codeGenInfo type="ModelRefInfoRepo.CodeGenInformation" uuid="abede99f-178f-444f-b6ab-fbc209d4aa7c">
      <DWorkTypeName>kqdtm1plmi2</DWorkTypeName>
    </codeGenInfo>
    <compiledVariantInfos type="ModelRefInfoRepo.CompiledVariantInfoMap" uuid="2bdfa6ea-492b-4fee-b98c-ab1f803a27d1"/>
    <configSettingsForConsistencyChecks type="ModelRefInfoRepo.ConfigSettingsForConsistencyChecks" uuid="1fcbfe0a-0cea-4c7d-9507-1246ad9e289e">
      <consistentOutportInitialization>true</consistentOutportInitialization>
      <fixedStepSize>.01</fixedStepSize>
      <frameDiagnosticSetting>2</frameDiagnosticSetting>
      <hasHybridSampleTime>true</hasHybridSampleTime>
      <signalLoggingSaveFormat>2</signalLoggingSaveFormat>
      <simSIMDOptimization>1</simSIMDOptimization>
      <solverName>ode3</solverName>
      <solverType>SOLVER_TYPE_FIXEDSTEP</solverType>
      <hardwareSettings type="ModelRefInfoRepo.HardwareSettings" uuid="7278bfd5-5203-4a48-9256-543a36c31cb2">
        <prodBitPerChar>8</prodBitPerChar>
        <prodBitPerDouble>64</prodBitPerDouble>
        <prodBitPerFloat>32</prodBitPerFloat>
        <prodBitPerInt>32</prodBitPerInt>
        <prodBitPerLong>32</prodBitPerLong>
        <prodBitPerLongLong>64</prodBitPerLongLong>
        <prodBitPerPointer>64</prodBitPerPointer>
        <prodBitPerPtrDiffT>64</prodBitPerPtrDiffT>
        <prodBitPerShort>16</prodBitPerShort>
        <prodBitPerSizeT>64</prodBitPerSizeT>
        <prodEndianess>1</prodEndianess>
        <prodShiftRight>true</prodShiftRight>
        <prodWordSize>64</prodWordSize>
      </hardwareSettings>
    </configSettingsForConsistencyChecks>
    <controllableInputRatesMap type="ModelRefInfoRepo.VarTsUIDMap" uuid="07bc7bf0-93bb-40df-8eb6-18ae42ee17dd"/>
    <controllableOutputRatesMap type="ModelRefInfoRepo.VarTsUIDMap" uuid="e66a31c4-b9c8-4d8e-9394-f623fbfd91a3"/>
    <dataPortGroup type="ModelRefInfoRepo.DataPortGroup" uuid="094e25ce-6f54-4e4c-a191-f46482f495f4">
      <compDataInputPorts>0</compDataInputPorts>
      <compDataOutputPorts>0</compDataOutputPorts>
      <dataInputPorts>0</dataInputPorts>
      <dataOutputPorts>0</dataOutputPorts>
    </dataPortGroup>
    <expFcnUnconnectedDataPortGroup type="ModelRefInfoRepo.DataPortGroup" uuid="6d85d797-76e5-4070-9dac-3a61077a0df7"/>
    <interfaceParameterInfo type="ModelRefInfoRepo.InterfaceParameterInfo" uuid="743fffd7-dd64-44ca-8a9f-1d4257a234d6">
      <globalVariables type="ModelRefInfoRepo.BuiltinParameter" uuid="6ce44dc9-5149-45d3-9739-d63fa10d9ef2">
        <dimensions>1</dimensions>
        <dimensions>1</dimensions>
        <isUsed>true</isUsed>
        <numDimensions>2</numDimensions>
        <parameterName>Fn</parameterName>
      </globalVariables>
      <globalVariables type="ModelRefInfoRepo.BuiltinParameter" uuid="c78e7988-c358-449b-a860-98e073d957f2">
        <dimensions>1</dimensions>
        <dimensions>1</dimensions>
        <isUsed>true</isUsed>
        <numDimensions>2</numDimensions>
        <parameterName>Tpulse</parameterName>
      </globalVariables>
      <globalVariables type="ModelRefInfoRepo.BuiltinParameter" uuid="3ed72735-cfb1-498e-8f55-b71d6d216e61">
        <dimensions>1</dimensions>
        <dimensions>1</dimensions>
        <isUsed>true</isUsed>
        <numDimensions>2</numDimensions>
        <parameterName>mib</parameterName>
      </globalVariables>
      <globalVariables type="ModelRefInfoRepo.BuiltinParameter" uuid="200e0116-7420-4d0f-946b-2f470730bfcc">
        <dimensions>1</dimensions>
        <dimensions>1</dimensions>
        <isUsed>true</isUsed>
        <numDimensions>2</numDimensions>
        <parameterName>peak_prop</parameterName>
      </globalVariables>
      <globalVariables type="ModelRefInfoRepo.BuiltinParameter" uuid="c82dbfd0-b9a5-4b8b-86c7-b8bdd414cd8e">
        <dimensions>1</dimensions>
        <dimensions>1</dimensions>
        <isUsed>true</isUsed>
        <numDimensions>2</numDimensions>
        <parameterName>tc</parameterName>
      </globalVariables>
    </interfaceParameterInfo>
    <messageInfo type="ModelRefInfoRepo.MessageInformation" uuid="213372d0-5e17-41f3-b861-6f51528d6d10"/>
    <methodInfo type="ModelRefInfoRepo.MethodExistenceInfo" uuid="495d9427-5768-424b-b459-62e8917a819f">
      <hasDerivMethod>true</hasDerivMethod>
      <hasForcingFunctionMethod>true</hasForcingFunctionMethod>
      <hasStartMethod>true</hasStartMethod>
      <hasSystemInitializeMethod>true</hasSystemInitializeMethod>
      <hasSystemResetMethod>true</hasSystemResetMethod>
      <hasTerminateMethod>true</hasTerminateMethod>
      <hasUpdateMethod>true</hasUpdateMethod>
    </methodInfo>
    <periodicEventPortUnsupportedBlockInfo type="ModelRefInfoRepo.PeriodicEventPortUnsupportedBlockInfo" uuid="9edfb7e6-d835-46ee-a3ab-8de88b1f6c23"/>
    <portGroupsRequireSameRate type="ModelRefInfoRepo.PortGroupsRequireSameRate" uuid="909a31f9-482c-4025-a44f-c08b968ec429">
      <DSMPortGroups type="ModelRefInfoRepo.NameToPortGroupIdxVectMap" uuid="ed0b526a-e5f4-4cd5-b43a-526571e93435"/>
      <GlobalDSMPortGroups type="ModelRefInfoRepo.NameToPortGroupIdxVectMap" uuid="8eb86fdc-401f-495f-b685-4512961962d7"/>
      <mergedPortGroups type="ModelRefInfoRepo.NameToPortGroupIdxVectMap" uuid="c30a8843-5965-4fe7-b6b3-9b275d0d983e"/>
    </portGroupsRequireSameRate>
    <rateBasedMdlGlobalDSMRateSpec type="ModelRefInfoRepo.GlobalDSMRateSpecMap" uuid="fd3d9b3d-d00a-4408-9b81-b0ed11c04002"/>
    <rateSpecOfGlobalDSMAccessedByDescExpFcnMdlMap type="ModelRefInfoRepo.GlobalDSMRateSpecMap" uuid="1d281fe6-b92f-4895-b606-ddf1fe704905"/>
    <rootBlockDiagramInterface type="ci.Model" uuid="ee9a09bf-5ef3-4a14-bfbe-8719b412f6df">
      <p_RootComponentInterface type="ci.ComponentInterface" uuid="6253cc76-0356-4135-a841-3ddcbf5b4cdb">
        <p_InputPorts type="ci.SignalInterface" uuid="59ee4199-6a52-4cdd-b912-a4a6266a2db4">
          <p_ComputedNumericDimensions>1.0</p_ComputedNumericDimensions>
          <p_ComputedSampleTime>0.0</p_ComputedSampleTime>
          <p_ComputedSampleTime>0.0</p_ComputedSampleTime>
          <p_Name>t_cmd</p_Name>
        </p_InputPorts>
        <p_Name>Propulsor</p_Name>
        <p_OutputPorts type="ci.SignalInterface" uuid="e5548258-fb17-48d5-be4a-e91a78454397">
          <p_ComputedNumericDimensions>1.0</p_ComputedNumericDimensions>
          <p_ComputedSampleTime>0.0</p_ComputedSampleTime>
          <p_ComputedSampleTime>0.0</p_ComputedSampleTime>
          <p_Name>y</p_Name>
        </p_OutputPorts>
        <p_Type>ROOT</p_Type>
      </p_RootComponentInterface>
    </rootBlockDiagramInterface>
    <simulinkFunctions type="ModelRefInfoRepo.SimulinkFunctions" uuid="0245b25d-eebd-442c-b0aa-e4c8c6cc1da6">
      <compSimulinkFunctionCatalog></compSimulinkFunctionCatalog>
    </simulinkFunctions>
    <sltpContext type="sltp.mm.core.Context" uuid="37a0356c-da5b-414c-85a0-f80e4efc65c4">
      <globalData type="sltp.mm.core.GlobalData" uuid="eba95619-d8dc-4b08-b47c-e6dd9351e868">
        <dataName>portF_real</dataName>
        <type>RootInport</type>
      </globalData>
      <globalData type="sltp.mm.core.GlobalData" uuid="2f6096f4-85cd-4af9-a83c-3b40fdb5584e">
        <dataName>portt_cmd</dataName>
        <type>RootInport</type>
      </globalData>
      <globalData type="sltp.mm.core.GlobalData" uuid="10044e0c-5449-4a88-8540-98b9055ecd4c">
        <dataName>porty</dataName>
        <type>RootOutport</type>
      </globalData>
      <priorityDirection>HighNumberLast</priorityDirection>
      <defaultEventBehavior type="sltp.mm.core.EventBehavior" uuid="c7cbb973-b128-4b18-bde7-33e0707db35a"/>
      <editorState type="sltp.mm.core.EditorState" uuid="8718e0d6-6bf3-4fba-bbe8-9a344c33872f">
        <isSynchronized>true</isSynchronized>
        <panelState type="sltp.mm.core.EditorPanelState" uuid="a71867ea-673d-4cab-afd0-c4db8bc1a2e7"/>
      </editorState>
      <rootTask type="sltp.mm.core.Task" uuid="f68adad9-fdce-4be7-b08f-cd77a5388e41">
        <context type="sltp.mm.core.Context" uuid="37a0356c-da5b-414c-85a0-f80e4efc65c4"/>
        <explicit>false</explicit>
        <name>Default</name>
        <priority>-2147483648</priority>
        <subgraph type="sltp.mm.core.Graph" uuid="14f15ff8-15db-44a7-86bf-eb78917b2bed">
          <tasks type="sltp.mm.core.Task" uuid="41a93355-6f5c-4d6b-bdb8-25f731703457">
            <baseTask>true</baseTask>
            <context type="sltp.mm.core.Context" uuid="37a0356c-da5b-414c-85a0-f80e4efc65c4"/>
            <explicit>false</explicit>
            <id>1</id>
            <isTimed>true</isTimed>
            <name>Cont</name>
            <priority>40</priority>
            <rates type="sltp.mm.core.Rate" uuid="b0252fa8-fcda-4fd3-931b-9ddc14de5170">
              <annotation>Cont</annotation>
              <color>255</color>
              <hasBlocks>true</hasBlocks>
              <identifier>Continuous00</identifier>
              <rateIndex>0</rateIndex>
              <rateSpec type="sltp.mm.core.RateSpec">
                <period>0.0</period>
              </rateSpec>
              <sti>0</sti>
            </rates>
            <rates type="sltp.mm.core.Rate" uuid="db845037-eebf-4d41-8fa5-5d8ccc995a00">
              <annotation>D1</annotation>
              <color>-12240129</color>
              <hasBlocks>true</hasBlocks>
              <rateIndex>1</rateIndex>
              <rateSpec type="sltp.mm.core.RateSpec">
                <period>.01</period>
              </rateSpec>
              <sti>1</sti>
            </rates>
          </tasks>
        </subgraph>
      </rootTask>
    </sltpContext>
    <stateWriterToOwnerMap type="ModelRefInfoRepo.StateWriterInfo" uuid="b38666d5-6147-4b8d-bd8d-51359e631dc6"/>
    <stoClientDataRegistry type="sto.ClientDataRegistry" uuid="cf253966-bda4-496c-9b86-04d7ee53c768">
      <dataSets type="sto.ClientClockNamedDataSet" uuid="a36c2a47-5a64-456b-827e-dc123f39ae34">
        <tag>sltpEvents</tag>
      </dataSets>
      <dataSets type="sto.ClientTaskHierarchyElementNamedDataSet" uuid="82aea6e4-414f-48fd-94cc-6dcfbccb7039">
        <tag>sltpTaskGroups</tag>
      </dataSets>
      <dataSets type="sto.ClientTaskHierarchyElementNamedDataSet" uuid="5654bc0d-f85c-40a5-ac55-8bc2dc80b7f5">
        <dSet type="ModelRefInfoRepo.SltpTaskData" uuid="53f2404c-90d3-479d-b7e7-89d30cc5dd6b"/>
        <tSet type="ModelRefInfoRepo.SltpTaskData" uuid="53f2404c-90d3-479d-b7e7-89d30cc5dd6b">
          <dataName>Cont</dataName>
          <linkedSet type="sto.ClientTaskHierarchyElementNamedDataSet" uuid="5654bc0d-f85c-40a5-ac55-8bc2dc80b7f5"/>
          <id type="sto.TaskHierarchyElementId">
            <clockId>Propulsor::defaultTimer</clockId>
            <id>_task0</id>
          </id>
        </tSet>
        <tag>sltpTasks</tag>
      </dataSets>
    </stoClientDataRegistry>
    <typeTable type="type_info.TypeTable" uuid="ccfd702b-cb83-41ec-92e7-fdbf8ed4f288">
      <Types type="type_info.Type" uuid="57d3934c-5a2e-44f2-9c83-ed527e17656e">
        <Name>action</Name>
      </Types>
      <Types type="type_info.NumericType" uuid="58635f2e-8658-4330-ab44-be06c7819767">
        <MxClassId>3</MxClassId>
        <Size>1</Size>
        <typeEnum>NUMERIC</typeEnum>
        <Name>boolean</Name>
      </Types>
      <Types type="type_info.NumericType" uuid="3d100cd5-6af5-4729-a6c4-1ec994ee9f81">
        <DataTypeId>1</DataTypeId>
        <MxClassId>6</MxClassId>
        <Size>8</Size>
        <typeEnum>NUMERIC</typeEnum>
        <Name>double</Name>
      </Types>
      <Types type="type_info.Type" uuid="bf162312-24b6-4da5-ae8e-a8c287967856">
        <DataTypeId>17</DataTypeId>
        <Size>2552</Size>
        <Name>dsp_simulink_RandomSource1</Name>
      </Types>
      <Types type="type_info.Type" uuid="2f7fa229-9ab7-4f40-9127-33f73cd0b50e">
        <Name>fcn_call</Name>
      </Types>
      <Types type="type_info.NumericType" uuid="5f880716-6a13-4599-a4dc-dcf70dd3f3c5">
        <MxClassId>10</MxClassId>
        <Size>2</Size>
        <typeEnum>NUMERIC</typeEnum>
        <Name>int16</Name>
      </Types>
      <Types type="type_info.NumericType" uuid="49866c3a-1ed3-4c6e-98d6-8763693c125c">
        <MxClassId>12</MxClassId>
        <Size>4</Size>
        <Name>int32</Name>
      </Types>
      <Types type="type_info.FixedPointType" uuid="14a9db5d-bcc2-49fa-b3e1-11edcf5d0f03">
        <DataTypeId>15</DataTypeId>
        <Size>8</Size>
        <typeEnum>FIXPOINT</typeEnum>
        <Name>int64</Name>
      </Types>
      <Types type="type_info.NumericType" uuid="69c6687b-9831-4ba6-bacb-80a18a61aaeb">
        <MxClassId>8</MxClassId>
        <Size>1</Size>
        <typeEnum>NUMERIC</typeEnum>
        <Name>int8</Name>
      </Types>
      <Types type="type_info.Type" uuid="559229ef-7d04-42a4-af80-bd8ab679dc77">
        <Name>integer</Name>
      </Types>
      <Types type="type_info.Type" uuid="d35df176-f479-4bcd-b5d7-e728cc7cec16">
        <Name>physical_connection</Name>
      </Types>
      <Types type="type_info.Type" uuid="86bba0c2-f4b9-4cf7-9677-f5253c5e32dd">
        <Name>pointer</Name>
      </Types>
      <Types type="type_info.NumericType" uuid="9cc26e33-a156-4a73-a428-49b567f945d3">
        <MxClassId>7</MxClassId>
        <Size>4</Size>
        <typeEnum>NUMERIC</typeEnum>
        <Name>single</Name>
      </Types>
      <Types type="type_info.Type" uuid="488d28cd-611d-4fb6-b821-0e5542ada12b">
        <Name>timer_uint32_pair</Name>
      </Types>
      <Types type="type_info.NumericType" uuid="bce1cca6-2e0b-4af1-b770-a95befc38194">
        <MxClassId>11</MxClassId>
        <Size>2</Size>
        <typeEnum>NUMERIC</typeEnum>
        <Name>uint16</Name>
      </Types>
      <Types type="type_info.NumericType" uuid="d0eed8dd-5e91-457d-a8f3-461be9a6aeed">
        <MxClassId>13</MxClassId>
        <Size>4</Size>
        <typeEnum>NUMERIC</typeEnum>
        <Name>uint32</Name>
      </Types>
      <Types type="type_info.FixedPointType" uuid="ee2ce504-5ba8-4a77-8140-671302c04e41">
        <DataTypeId>16</DataTypeId>
        <Size>8</Size>
        <typeEnum>FIXPOINT</typeEnum>
        <Name>uint64</Name>
      </Types>
      <Types type="type_info.NumericType" uuid="2b974038-c2d2-499f-9d36-d910a6fb47bd">
        <MxClassId>9</MxClassId>
        <Size>1</Size>
        <typeEnum>NUMERIC</typeEnum>
        <Name>uint8</Name>
      </Types>
      <isInitialized>true</isInitialized>
    </typeTable>
    <varTsUIDMap type="ModelRefInfoRepo.VarTsUIDMap" uuid="8c8a0c5c-4780-416b-b4e2-9062840fff3c"/>
  </ModelRefInfoRepo.ModelRefInfoRoot>
</MF0>